alibabacloud_nas20170626/__init__.py
alibabacloud_nas20170626/client.py
alibabacloud_nas20170626/models/__init__.py
alibabacloud_nas20170626/models/_add_client_to_black_list_request.py
alibabacloud_nas20170626/models/_add_client_to_black_list_response.py
alibabacloud_nas20170626/models/_add_client_to_black_list_response_body.py
alibabacloud_nas20170626/models/_apply_auto_snapshot_policy_request.py
alibabacloud_nas20170626/models/_apply_auto_snapshot_policy_response.py
alibabacloud_nas20170626/models/_apply_auto_snapshot_policy_response_body.py
alibabacloud_nas20170626/models/_apply_data_flow_auto_refresh_request.py
alibabacloud_nas20170626/models/_apply_data_flow_auto_refresh_response.py
alibabacloud_nas20170626/models/_apply_data_flow_auto_refresh_response_body.py
alibabacloud_nas20170626/models/_attach_vsc_to_filesystems_request.py
alibabacloud_nas20170626/models/_attach_vsc_to_filesystems_response.py
alibabacloud_nas20170626/models/_attach_vsc_to_filesystems_response_body.py
alibabacloud_nas20170626/models/_cancel_auto_snapshot_policy_request.py
alibabacloud_nas20170626/models/_cancel_auto_snapshot_policy_response.py
alibabacloud_nas20170626/models/_cancel_auto_snapshot_policy_response_body.py
alibabacloud_nas20170626/models/_cancel_data_flow_auto_refresh_request.py
alibabacloud_nas20170626/models/_cancel_data_flow_auto_refresh_response.py
alibabacloud_nas20170626/models/_cancel_data_flow_auto_refresh_response_body.py
alibabacloud_nas20170626/models/_cancel_data_flow_sub_task_request.py
alibabacloud_nas20170626/models/_cancel_data_flow_sub_task_response.py
alibabacloud_nas20170626/models/_cancel_data_flow_sub_task_response_body.py
alibabacloud_nas20170626/models/_cancel_data_flow_task_request.py
alibabacloud_nas20170626/models/_cancel_data_flow_task_response.py
alibabacloud_nas20170626/models/_cancel_data_flow_task_response_body.py
alibabacloud_nas20170626/models/_cancel_dir_quota_request.py
alibabacloud_nas20170626/models/_cancel_dir_quota_response.py
alibabacloud_nas20170626-3.2.1.dist-info/LICENSE
alibabacloud_nas20170626-3.2.1.dist-info/METADATA
alibabacloud_nas20170626-3.2.1.dist-info/WHEEL
alibabacloud_nas20170626-3.2.1.dist-info/top_level.txt
alibabacloud_nas20170626-3.2.1.dist-info/RECORD
